{
  "annotations": {
    "list": [
      {
        "builtIn": 1,
        "datasource": "Prometheus",
        "enable": true,
        "hide": true,
        "iconColor": "rgba(0, 211, 255, 1)",
        "name": "Business Events",
        "target": {
          "limit": 100,
          "matchAny": false,
          "tags": ["business"],
          "type": "dashboard"
        },
        "type": "dashboard"
      }
    ]
  },
  "editable": true,
  "fiscalYearStartMonth": 0,
  "graphTooltip": 0,
  "id": null,
  "links": [
    {
      "asDropdown": false,
      "icon": "external link",
      "includeVars": false,
      "keepTime": false,
      "tags": [],
      "targetBlank": true,
      "title": "Executive Dashboard",
      "tooltip": "Switch to Executive View",
      "type": "link",
      "url": "/d/executive-overview/executive-overview"
    },
    {
      "asDropdown": false,
      "icon": "external link",
      "includeVars": false,
      "keepTime": false,
      "tags": [],
      "targetBlank": true,
      "title": "Cost Dashboard",
      "tooltip": "Switch to Cost View",
      "type": "link",
      "url": "/d/cost-optimization/cost-optimization"
    }
  ],
  "liveNow": false,
  "panels": [
    {
      "datasource": "Prometheus",
      "fieldConfig": {
        "defaults": {
          "color": {
            "mode": "thresholds"
          },
          "mappings": [],
          "thresholds": {
            "mode": "absolute",
            "steps": [
              {
                "color": "red",
                "value": null
              },
              {
                "color": "yellow",
                "value": 1000
              },
              {
                "color": "green",
                "value": 10000
              }
            ]
          },
          "unit": "short"
        }
      },
      "gridPos": {
        "h": 8,
        "w": 6,
        "x": 0,
        "y": 0
      },
      "id": 1,
      "options": {
        "colorMode": "value",
        "graphMode": "area",
        "justifyMode": "auto",
        "orientation": "auto",
        "reduceOptions": {
          "values": false,
          "calcs": [
            "lastNotNull"
          ],
          "fields": ""
        },
        "text": {},
        "textMode": "auto"
      },
      "pluginVersion": "8.5.0",
      "targets": [
        {
          "expr": "sum(increase(http_requests_total{job=\"sutazai-backend\",code=~\"2..\"}[1d]))",
          "interval": "",
          "legendFormat": "Daily Active Users",
          "refId": "A"
        }
      ],
      "title": "Daily Active API Calls",
      "type": "stat"
    },
    {
      "datasource": "Prometheus",
      "fieldConfig": {
        "defaults": {
          "color": {
            "mode": "thresholds"
          },
          "mappings": [],
          "thresholds": {
            "mode": "absolute",
            "steps": [
              {
                "color": "red",
                "value": null
              },
              {
                "color": "yellow",
                "value": 10
              },
              {
                "color": "green",
                "value": 50
              }
            ]
          },
          "unit": "short"
        }
      },
      "gridPos": {
        "h": 8,
        "w": 6,
        "x": 6,
        "y": 0
      },
      "id": 2,
      "options": {
        "colorMode": "value",
        "graphMode": "area",
        "justifyMode": "auto",
        "orientation": "auto",
        "reduceOptions": {
          "values": false,
          "calcs": [
            "lastNotNull"
          ],
          "fields": ""
        },
        "text": {},
        "textMode": "auto"
      },
      "pluginVersion": "8.5.0",
      "targets": [
        {
          "expr": "sum(up{job=~\"sutazai-.*agent.*\"})",
          "interval": "",
          "legendFormat": "Active AI Agents",
          "refId": "A"
        }
      ],
      "title": "Active AI Agents",
      "type": "stat"
    },
    {
      "datasource": "Prometheus",
      "fieldConfig": {
        "defaults": {
          "color": {
            "mode": "thresholds"
          },
          "mappings": [],
          "thresholds": {
            "mode": "absolute",
            "steps": [
              {
                "color": "green",
                "value": null
              },
              {
                "color": "yellow",
                "value": 95
              },
              {
                "color": "red",
                "value": 90
              }
            ]
          },
          "unit": "percent"
        }
      },
      "gridPos": {
        "h": 8,
        "w": 6,
        "x": 12,
        "y": 0
      },
      "id": 3,
      "options": {
        "colorMode": "value",
        "graphMode": "area",
        "justifyMode": "auto",
        "orientation": "auto",
        "reduceOptions": {
          "values": false,
          "calcs": [
            "lastNotNull"
          ],
          "fields": ""
        },
        "text": {},
        "textMode": "auto"
      },
      "pluginVersion": "8.5.0",
      "targets": [
        {
          "expr": "(sum(rate(http_requests_total{job=\"sutazai-backend\",code!~\"5..\"}[5m])) / sum(rate(http_requests_total{job=\"sutazai-backend\"}[5m]))) * 100",
          "interval": "",
          "legendFormat": "Service Quality",
          "refId": "A"
        }
      ],
      "title": "Service Quality (SLA)",
      "type": "stat"
    },
    {
      "datasource": "Prometheus",
      "fieldConfig": {
        "defaults": {
          "color": {
            "mode": "thresholds"
          },
          "mappings": [],
          "thresholds": {
            "mode": "absolute",
            "steps": [
              {
                "color": "green",
                "value": null
              },
              {
                "color": "yellow",
                "value": 500
              },
              {
                "color": "red",
                "value": 1000
              }
            ]
          },
          "unit": "ms"
        }
      },
      "gridPos": {
        "h": 8,
        "w": 6,
        "x": 18,
        "y": 0
      },
      "id": 4,
      "options": {
        "colorMode": "value",
        "graphMode": "area",
        "justifyMode": "auto",
        "orientation": "auto",
        "reduceOptions": {
          "values": false,
          "calcs": [
            "lastNotNull"
          ],
          "fields": ""
        },
        "text": {},
        "textMode": "auto"
      },
      "pluginVersion": "8.5.0",
      "targets": [
        {
          "expr": "histogram_quantile(0.95, sum(rate(http_request_duration_seconds_bucket{job=\"sutazai-backend\"}[5m])) by (le)) * 1000",
          "interval": "",
          "legendFormat": "User Experience Score",
          "refId": "A"
        }
      ],
      "title": "User Experience (P95 Latency)",
      "type": "stat"
    },
    {
      "datasource": "Prometheus",
      "fieldConfig": {
        "defaults": {
          "color": {
            "mode": "palette-classic"
          },
          "custom": {
            "axisLabel": "",
            "axisPlacement": "auto",
            "barAlignment": 0,
            "drawStyle": "line",
            "fillOpacity": 10,
            "gradientMode": "none",
            "hideFrom": {
              "legend": false,
              "tooltip": false,
              "vis": false
            },
            "lineInterpolation": "linear",
            "lineWidth": 1,
            "pointSize": 5,
            "scaleDistribution": {
              "type": "linear"
            },
            "showPoints": "never",
            "spanNulls": false,
            "stacking": {
              "group": "A",
              "mode": "none"
            },
            "thresholdsStyle": {
              "mode": "off"
            }
          },
          "mappings": [],
          "thresholds": {
            "mode": "absolute",
            "steps": [
              {
                "color": "green",
                "value": null
              },
              {
                "color": "red",
                "value": 80
              }
            ]
          },
          "unit": "reqps"
        }
      },
      "gridPos": {
        "h": 8,
        "w": 12,
        "x": 0,
        "y": 8
      },
      "id": 5,
      "options": {
        "legend": {
          "calcs": [],
          "displayMode": "list",
          "placement": "bottom"
        },
        "tooltip": {
          "mode": "single",
          "sort": "none"
        }
      },
      "targets": [
        {
          "expr": "sum(rate(http_requests_total{job=\"sutazai-backend\"}[5m]))",
          "interval": "",
          "legendFormat": "Total Requests",
          "refId": "A"
        },
        {
          "expr": "sum(rate(http_requests_total{job=\"sutazai-backend\",code=~\"2..\"}[5m]))",
          "interval": "",
          "legendFormat": "Successful Requests",
          "refId": "B"
        }
      ],
      "title": "API Usage Growth",
      "type": "timeseries"
    },
    {
      "datasource": "Prometheus",
      "fieldConfig": {
        "defaults": {
          "color": {
            "mode": "palette-classic"
          },
          "custom": {
            "axisLabel": "",
            "axisPlacement": "auto",
            "barAlignment": 0,
            "drawStyle": "line",
            "fillOpacity": 10,
            "gradientMode": "none",
            "hideFrom": {
              "legend": false,
              "tooltip": false,
              "vis": false
            },
            "lineInterpolation": "linear",
            "lineWidth": 1,
            "pointSize": 5,
            "scaleDistribution": {
              "type": "linear"
            },
            "showPoints": "never",
            "spanNulls": false,
            "stacking": {
              "group": "A",
              "mode": "none"
            },
            "thresholdsStyle": {
              "mode": "off"
            }
          },
          "mappings": [],
          "thresholds": {
            "mode": "absolute",
            "steps": [
              {
                "color": "green",
                "value": null
              },
              {
                "color": "red",
                "value": 80
              }
            ]
          },
          "unit": "short"
        }
      },
      "gridPos": {
        "h": 8,
        "w": 12,
        "x": 12,
        "y": 8
      },
      "id": 6,
      "options": {
        "legend": {
          "calcs": [],
          "displayMode": "list",
          "placement": "bottom"
        },
        "tooltip": {
          "mode": "single",
          "sort": "none"
        }
      },
      "targets": [
        {
          "expr": "sum(up{job=~\"sutazai-.*agent.*\"}) by (job)",
          "interval": "",
          "legendFormat": "{{job}}",
          "refId": "A"
        }
      ],
      "title": "AI Agent Utilization",
      "type": "timeseries"
    },
    {
      "datasource": "Prometheus",
      "fieldConfig": {
        "defaults": {
          "color": {
            "mode": "palette-classic"
          },
          "custom": {
            "hideFrom": {
              "legend": false,
              "tooltip": false,
              "vis": false
            }
          },
          "mappings": []
        }
      },
      "gridPos": {
        "h": 8,
        "w": 12,
        "x": 0,
        "y": 16
      },
      "id": 7,
      "options": {
        "legend": {
          "displayMode": "list",
          "placement": "bottom"
        },
        "pieType": "pie",
        "reduceOptions": {
          "values": false,
          "calcs": [
            "lastNotNull"
          ],
          "fields": ""
        },
        "tooltip": {
          "mode": "single",
          "sort": "none"
        }
      },
      "targets": [
        {
          "expr": "sum by (method) (rate(http_requests_total{job=\"sutazai-backend\"}[1h]))",
          "interval": "",
          "legendFormat": "{{method}}",
          "refId": "A"
        }
      ],
      "title": "Feature Usage Distribution",
      "type": "piechart"
    },
    {
      "datasource": "Prometheus",
      "fieldConfig": {
        "defaults": {
          "color": {
            "mode": "palette-classic"
          },
          "custom": {
            "axisLabel": "",
            "axisPlacement": "auto",
            "barAlignment": 0,
            "drawStyle": "line",
            "fillOpacity": 10,
            "gradientMode": "none",
            "hideFrom": {
              "legend": false,
              "tooltip": false,
              "vis": false
            },
            "lineInterpolation": "linear",
            "lineWidth": 1,
            "pointSize": 5,
            "scaleDistribution": {
              "type": "linear"
            },
            "showPoints": "never",
            "spanNulls": false,
            "stacking": {
              "group": "A",
              "mode": "none"
            },
            "thresholdsStyle": {
              "mode": "off"
            }
          },
          "mappings": [],
          "thresholds": {
            "mode": "absolute",
            "steps": [
              {
                "color": "green",
                "value": null
              },
              {
                "color": "red",
                "value": 80
              }
            ]
          },
          "unit": "percent"
        }
      },
      "gridPos": {
        "h": 8,
        "w": 12,
        "x": 12,
        "y": 16
      },
      "id": 8,
      "options": {
        "legend": {
          "calcs": [],
          "displayMode": "list",
          "placement": "bottom"
        },
        "tooltip": {
          "mode": "single",
          "sort": "none"
        }
      },
      "targets": [
        {
          "expr": "(sum(rate(http_requests_total{job=\"sutazai-backend\",code!~\"5..\"}[5m])) / sum(rate(http_requests_total{job=\"sutazai-backend\"}[5m]))) * 100",
          "interval": "",
          "legendFormat": "Service Reliability",
          "refId": "A"
        },
        {
          "expr": "avg(up{job=~\"sutazai-.*\"}) * 100",
          "interval": "",
          "legendFormat": "System Availability",
          "refId": "B"
        }
      ],
      "title": "Business SLAs",
      "type": "timeseries"
    },
    {
      "datasource": "Prometheus",
      "fieldConfig": {
        "defaults": {
          "color": {
            "mode": "palette-classic"
          },
          "custom": {
            "axisLabel": "",
            "axisPlacement": "auto",
            "barAlignment": 0,
            "drawStyle": "line",
            "fillOpacity": 10,
            "gradientMode": "none",
            "hideFrom": {
              "legend": false,
              "tooltip": false,
              "vis": false
            },
            "lineInterpolation": "linear",
            "lineWidth": 1,
            "pointSize": 5,
            "scaleDistribution": {
              "type": "linear"
            },
            "showPoints": "never",
            "spanNulls": false,
            "stacking": {
              "group": "A",
              "mode": "none"
            },
            "thresholdsStyle": {
              "mode": "off"
            }
          },
          "mappings": [],
          "thresholds": {
            "mode": "absolute",
            "steps": [
              {
                "color": "green",
                "value": null
              },
              {
                "color": "red",
                "value": 80
              }
            ]
          },
          "unit": "reqps"
        }
      },
      "gridPos": {
        "h": 8,
        "w": 12,
        "x": 0,
        "y": 24
      },
      "id": 9,
      "options": {
        "legend": {
          "calcs": [],
          "displayMode": "list",
          "placement": "bottom"
        },
        "tooltip": {
          "mode": "single",
          "sort": "none"
        }
      },
      "targets": [
        {
          "expr": "sum(increase(http_requests_total{job=\"sutazai-backend\",code=~\"2..\"}[1h]))",
          "interval": "",
          "legendFormat": "Hourly Success Volume",
          "refId": "A"
        },
        {
          "expr": "sum(increase(http_requests_total{job=\"sutazai-backend\",code=~\"4..|5..\"}[1h]))",
          "interval": "",
          "legendFormat": "Hourly Error Volume",
          "refId": "B"
        }
      ],
      "title": "Business Volume Metrics",
      "type": "timeseries"
    },
    {
      "datasource": "Prometheus",
      "fieldConfig": {
        "defaults": {
          "color": {
            "mode": "palette-classic"
          },
          "custom": {
            "axisLabel": "",
            "axisPlacement": "auto",
            "barAlignment": 0,
            "drawStyle": "line",
            "fillOpacity": 10,
            "gradientMode": "none",
            "hideFrom": {
              "legend": false,
              "tooltip": false,
              "vis": false
            },
            "lineInterpolation": "linear",
            "lineWidth": 1,
            "pointSize": 5,
            "scaleDistribution": {
              "type": "linear"
            },
            "showPoints": "never",
            "spanNulls": false,
            "stacking": {
              "group": "A",
              "mode": "none"
            },
            "thresholdsStyle": {
              "mode": "off"
            }
          },
          "mappings": [],
          "thresholds": {
            "mode": "absolute",
            "steps": [
              {
                "color": "green",
                "value": null
              },
              {
                "color": "red",
                "value": 80
              }
            ]
          },
          "unit": "short"
        }
      },
      "gridPos": {
        "h": 8,
        "w": 12,
        "x": 12,
        "y": 24
      },
      "id": 10,
      "options": {
        "legend": {
          "calcs": [],
          "displayMode": "list",
          "placement": "bottom"
        },
        "tooltip": {
          "mode": "single",
          "sort": "none"
        }
      },
      "targets": [
        {
          "expr": "postgres_stat_database_tup_inserted{datname=\"sutazai\"}",
          "interval": "",
          "legendFormat": "New Records Created",
          "refId": "A"
        },
        {
          "expr": "postgres_stat_database_tup_updated{datname=\"sutazai\"}",
          "interval": "",
          "legendFormat": "Records Updated",
          "refId": "B"
        },
        {
          "expr": "postgres_stat_database_tup_deleted{datname=\"sutazai\"}",
          "interval": "",
          "legendFormat": "Records Deleted",
          "refId": "C"
        }
      ],
      "title": "Data Activity Metrics",
      "type": "timeseries"
    }
  ],
  "refresh": "30s",
  "schemaVersion": 27,
  "style": "dark",
  "tags": [
    "business",
    "revenue",
    "usage"
  ],
  "templating": {
    "list": []
  },
  "time": {
    "from": "now-24h",
    "to": "now"
  },
  "timepicker": {},
  "timezone": "",
  "title": "Business Metrics Dashboard",
  "uid": "business-metrics",
  "version": 1
}