{
  "monitoring": {
    "enabled": true,
    "check_interval_minutes": 60,
    "backup_max_age_hours": 26,
    "backup_size_deviation_percent": 50,
    "storage_threshold_percent": 85,
    "retention_days": 30
  },
  "alerts": {
    "enabled": true,
    "methods": ["system_log", "email"],
    "severity_levels": ["critical", "warning", "info"],
    "rate_limiting": {
      "max_alerts_per_hour": 10,
      "cooldown_minutes": 30
    }
  },
  "email": {
    "enabled": false,
    "smtp_host": "localhost",
    "smtp_port": 587,
    "smtp_user": "backups@sutazai.local",
    "smtp_password_env": "BACKUP_SMTP_PASSWORD",
    "from_address": "backups@sutazai.local",
    "to_addresses": ["admin@sutazai.local"],
    "use_tls": true
  },
  "slack": {
    "enabled": false,
    "webhook_url_env": "BACKUP_SLACK_WEBHOOK",
    "channel": "#backups",
    "username": "SutazAI Backup Monitor"
  },
  "webhook": {
    "enabled": false,
    "url": "",
    "method": "POST",
    "headers": {},
    "timeout": 30
  },
  "sms": {
    "enabled": false,
    "service": "twilio",
    "account_sid_env": "TWILIO_ACCOUNT_SID",
    "auth_token_env": "TWILIO_AUTH_TOKEN",
    "from_number": "",
    "to_numbers": []
  },
  "health_checks": {
    "backup_freshness": true,
    "storage_usage": true,
    "verification_status": true,
    "offsite_replication": true,
    "restore_testing": true
  }
}